RaspberryPiVcgencmd/RaspberryPiVcgencmd.py
RaspberryPiVcgencmd/Vcgencmd.py
RaspberryPiVcgencmd/__init__.py
RaspberryPiVcgencmd-1.0.1.dist-info/LICENSE
RaspberryPiVcgencmd-1.0.1.dist-info/METADATA
RaspberryPiVcgencmd-1.0.1.dist-info/WHEEL
RaspberryPiVcgencmd-1.0.1.dist-info/top_level.txt
RaspberryPiVcgencmd-1.0.1.dist-info/RECORD
