Metadata-Version: 2.1
Name: RaspberryPiVcgencmd
Version: 1.0.1
Summary: Python binding for the Raspberry Pi Vcgencmd command line executable
Home-page: https://github.com/chewett/RaspberryPiVcgencmd
Author: Christopher Hewett
Author-email: chewett@hotmail.co.uk
License: MIT
Platform: UNKNOWN
Classifier: Programming Language :: Python :: 3
Classifier: License :: OSI Approved :: MIT License
Classifier: Operating System :: OS Independent
